graphene_protector/__init__.py
graphene_protector/base.py
graphene_protector/django/base.py
graphene_protector/django/graphene.py
graphene_protector/django/strawberry.py
graphene_protector/graphene.py
graphene_protector/misc.py
graphene_protector/strawberry.py
graphene_protector-0.12.1.dist-info/LICENSE
graphene_protector-0.12.1.dist-info/METADATA
graphene_protector-0.12.1.dist-info/WHEEL
graphene_protector-0.12.1.dist-info/RECORD
